fprime/__init__.py
fprime/constants.py
fprime/common/__init__.py
fprime/common/error.py
fprime/common/models/__init__.py
fprime/common/models/serialize/__init__.py
fprime/common/models/serialize/array_type.py
fprime/common/models/serialize/bool_type.py
fprime/common/models/serialize/enum_type.py
fprime/common/models/serialize/numerical_types.py
fprime/common/models/serialize/serializable_type.py
fprime/common/models/serialize/string_type.py
fprime/common/models/serialize/time_type.py
fprime/common/models/serialize/type_base.py
fprime/common/models/serialize/type_exceptions.py
fprime/fbuild/__init__.py
fprime/fbuild/builder.py
fprime/fbuild/cmake.py
fprime/fbuild/settings.py
fprime/util/__init__.py
fprime/util/__main__.py
fprime/util/build_helper.py
fprime-1.5.4.dev0.dist-info/METADATA
fprime-1.5.4.dev0.dist-info/WHEEL
fprime-1.5.4.dev0.dist-info/entry_points.txt
fprime-1.5.4.dev0.dist-info/top_level.txt
fprime-1.5.4.dev0.dist-info/RECORD
